msspeech/__init__.py
msspeech/__main__.py
msspeech/voices_list.json
msspeech-3.7.12.dist-info/METADATA
msspeech-3.7.12.dist-info/WHEEL
msspeech-3.7.12.dist-info/entry_points.txt
msspeech-3.7.12.dist-info/RECORD
