Metadata-Version: 2.1
Name: msspeech
Version: 3.7.12
Summary: not official API for Microsoft speech synthesis from Microsoft Edge web browser read aloud
Home-page: https://github.com/alekssamos/msspeech
Author: Alexey
Author-email: aleks-samos@yandex.ru
Requires-Python: >=3.7,<3.12
Classifier: Programming Language :: Python :: 3
Classifier: Programming Language :: Python :: 3.7
Classifier: Programming Language :: Python :: 3.8
Classifier: Programming Language :: Python :: 3.9
Classifier: Programming Language :: Python :: 3.10
Classifier: Programming Language :: Python :: 3.11
Requires-Dist: aiofiles (>0.8.0)
Requires-Dist: aiohttp (>3.8.1)
Requires-Dist: click (>8.0.2)
Project-URL: Bug Tracker, https://github.com/alekssamos/msspeech/issues
Project-URL: Repository, https://github.com/alekssamos/msspeech
